MANIFEST.in
README.md
README.txt
__about__.py
setup.py
wsgisubdomain.py
tests/requirements.txt
tests/test_wsgisubdomain.py
wsgisubdomain.egg-info/PKG-INFO
wsgisubdomain.egg-info/SOURCES.txt
wsgisubdomain.egg-info/dependency_links.txt
wsgisubdomain.egg-info/top_level.txt