Metadata-Version: 1.1
Name: wsgisubdomain
Version: 0.11
Summary: A WSGI application dispatcher for subdomain handling
Home-page: https://github.com/xsleonard/wsgisubdomain
Author: Steve Leonard
Author-email: sleonard76@gmail.com
License: MIT
Keywords: wsgi subdomain
Platform: any
Classifier: Development Status :: 4 - Beta
Classifier: Intended Audience :: Developers
Classifier: Programming Language :: Python
Classifier: Programming Language :: Python :: 2.6
Classifier: Programming Language :: Python :: 2.7
Classifier: Programming Language :: Python :: 3
Classifier: Programming Language :: Python :: 3.2
Classifier: Programming Language :: Python :: 3.3
Classifier: Programming Language :: Python :: Implementation :: PyPy
Classifier: Operating System :: OS Independent
Classifier: Topic :: Internet :: WWW/HTTP
Classifier: Topic :: Software Development :: Libraries :: Python Modules
Classifier: License :: OSI Approved :: MIT License
